mytree/__init__.py
mytree/bijectors.py
mytree/mytree.py
mytree/param.py
mytree-0.1.0.dist-info/LICENSE
mytree-0.1.0.dist-info/METADATA
mytree-0.1.0.dist-info/WHEEL
mytree-0.1.0.dist-info/top_level.txt
mytree-0.1.0.dist-info/zip-safe
mytree-0.1.0.dist-info/RECORD
