Metadata-Version: 2.1
Name: mytree
Version: 0.1.0
Summary: Module pytrees that cleanly handle parameter trainability and transformations for JAX models.
Author: Daniel Dodd
Author-email: daniel_dodd@icloud.com
License: MIT
Requires-Python: >=3.9
License-File: LICENSE
Requires-Dist: jax (>=0.4.1)
Requires-Dist: jaxlib (>=0.4.1)
Requires-Dist: simple-pytree (==0.1.6)
Provides-Extra: dev
Requires-Dist: pytest ; extra == 'dev'
Requires-Dist: pre-commit ; extra == 'dev'
Requires-Dist: pytest-cov ; extra == 'dev'
Requires-Dist: flax ; extra == 'dev'
